camelot_frs/__init__.py
camelot_frs/algorithms.py
camelot_frs/camelot_demo.py
camelot_frs/camelot_frs.py
camelot_frs/camelot_script.py
camelot_frs/expression_analysis.py
camelot_frs/pgdb_api.py
camelot_frs/pgdb_loader.py
camelot_frs/tests.py
camelot_frs-0.0.2.dist-info/LICENSE
camelot_frs-0.0.2.dist-info/METADATA
camelot_frs-0.0.2.dist-info/WHEEL
camelot_frs-0.0.2.dist-info/top_level.txt
camelot_frs-0.0.2.dist-info/RECORD
