Metadata-Version: 2.1
Name: camelot-frs
Version: 0.0.2
Summary: A frame representation system in Python.
Home-page: https://bitbucket.org/tomeraltman/camelot-frs/
Author: Tomer Altman
Author-email: camelot@me.tomeraltman.net
License: UNKNOWN
Platform: UNKNOWN
Classifier: Programming Language :: Python :: 3
Classifier: License :: OSI Approved :: Mozilla Public License 2.0 (MPL 2.0)
Classifier: Operating System :: OS Independent
Requires-Python: >=3.6
Requires-Dist: scipy
